Url91/__init__.py
Url91-0.0.1.dist-info/METADATA
Url91-0.0.1.dist-info/WHEEL
Url91-0.0.1.dist-info/top_level.txt
Url91-0.0.1.dist-info/RECORD
